natscale-0.1.2.dist-info/METADATA
natscale-0.1.2.dist-info/WHEEL
natscale-0.1.2.dist-info/entry_points.txt
natscale/__init__.py
natscale/cli/__init__.py
natscale/cli/push.py
natscale/cli/version.py
natscale/task/__init__.py
natscale/task/config.py
natscale/task/iter.py
natscale/task/iter_async.py
natscale/task/msg.py
natscale/task/push.py
natscale/utils/__init__.py
natscale/utils/helper.py
natscale-0.1.2.dist-info/RECORD
