Metadata-Version: 2.1
Name: natscale
Version: 0.1.2
Author-Email: "TX.Mao" <mtianxiang@gmail.com>
License: MIT
Requires-Python: >=3.12
Requires-Dist: loguru>=0.7.0
Requires-Dist: typer>=0.15.2
Requires-Dist: nats-py>=2.12.0
Requires-Dist: tqdm>=4.67.1
Requires-Dist: pyyaml>=6.0.3
Requires-Dist: faststream>=0.6.4
Requires-Dist: anyio>=4.12.0
